{
	"name": "RestResource_ds",
	"properties": {
		"linkedServiceName": {
			"referenceName": "RestService_ls",
			"type": "LinkedServiceReference"
		},
		"parameters": {
			"userToken": {
				"type": "String"
			},
			"filename": {
				"type": "String"
			},
			"setnum": {
				"type": "string"
			}
		},
		"annotations": [],
		"type": "RestResource",
		"typeProperties": {
			"relativeUrl": {
				"value": "@concat(dataset().userToken,'/',dataset().filename,'/',dataset().setnum)",
				"type": "Expression"
			}
		},
		"schema": []
	}
}